djangoaddressesapp/__init__.py
djangoaddressesapp/admin.py
djangoaddressesapp/apps.py
djangoaddressesapp/models.py
djangoaddressesapp/management/__init__.py
djangoaddressesapp/management/commands/__init__.py
djangoaddressesapp/management/commands/addresses_initialize_database.py
djangoaddressesapp/migrations/0001_initial.py
djangoaddressesapp/migrations/__init__.py
djangoaddressesapp-0.0.6.dist-info/LICENSE.txt
djangoaddressesapp-0.0.6.dist-info/METADATA
djangoaddressesapp-0.0.6.dist-info/WHEEL
djangoaddressesapp-0.0.6.dist-info/top_level.txt
djangoaddressesapp-0.0.6.dist-info/RECORD
